confai/__init__.py
confai/decorator.py
confai/evaluate.py
confai/experiments.py
confai/output.py
confai/utils.py
confai/models/__init__.py
confai/models/callbacks.py
confai/models/core.py
confai/models/functions.py
confai/models/nn_core.py
confai/models/schema.py
confai/models/torch_core.py
confai/models/text_cls/__init__.py
confai/models/text_cls/cls_token_cls.py
confai/models/text_cls/common.py
confai/models/text_cls/mlm_cls.py
confai/models/text_gen/__init__.py
confai/models/text_gen/common.py
confai/models/text_gen/transformer_gen.py
confai/models/text_span_cls/__init__.py
confai/models/text_span_cls/common.py
confai/models/text_span_cls/seq_labeling.py
tests/__init__.py
tests/test_core.py
tests/test_decorator.py
tests/test_schema.py
tests/test_utils.py
confai-0.0.6.dist-info/METADATA
confai-0.0.6.dist-info/WHEEL
confai-0.0.6.dist-info/dependency_links.txt
confai-0.0.6.dist-info/top_level.txt
confai-0.0.6.dist-info/RECORD
